MANIFEST.in
README.txt
setup.py
PythonTest/__init__.py
justatestpasswordgenerator2.egg-info/PKG-INFO
justatestpasswordgenerator2.egg-info/SOURCES.txt
justatestpasswordgenerator2.egg-info/dependency_links.txt
justatestpasswordgenerator2.egg-info/top_level.txt