Metadata-Version: 1.1
Name: justatestpasswordgenerator2
Version: 1.0.0
Summary: A random password generator
Home-page: UNKNOWN
Author: Joseph Keyes
Author-email: josephkeyes404@gmail.com
License: MIT
Keywords: password,generator,random
Platform: UNKNOWN
Classifier: Development Status :: 5 - Production/Stable
Classifier: Intended Audience :: Education
Classifier: Operating System :: Microsoft :: Windows :: Windows 10
Classifier: License :: OSI Approved :: MIT License
Classifier: Programming Language :: Python :: 3
